<?xml version="1.0" encoding="UTF-8"?>
<!DOCTYPE mapper PUBLIC "-//mybatis.org//DTD Mapper 3.0//EN" "http://mybatis.org/dtd/mybatis-3-mapper.dtd" >
<mapper namespace="com.example.zuer02.dao.DictInfoDao" >

    <resultMap id="BaseResultMap" type="com.zuer.movieprojectdict.entity.Dict" >
        <id column="DICT_ID" property="dictId" jdbcType="VARCHAR" />
        <result column="DICT_TYPE" property="dictType" jdbcType="VARCHAR" />
        <result column="DICT_TYPE_CONTENT" property="dictTypeContent" jdbcType="VARCHAR" />
        <result column="DICT_CODE" property="dictCode" jdbcType="VARCHAR" />
        <result column="DICT_VALUE" property="dictValue" jdbcType="VARCHAR" />
        <result column="CRT_DATE" property="crtTime" jdbcType="VARCHAR" />
        <result column="ALT_DATE" property="altTime" jdbcType="VARCHAR" />
    </resultMap>

    <insert id="addDictInfo" parameterType="com.zuer.movieprojectdict.entity.Dict">

        insert into DICT_INFO
        (DICT_ID,DICT_TYPE,DICT_TYPE_CONTENT,DICT_CODE,DICT_VALUE,CRT_DATE,ALT_DATE)
        values(
        #{dictId,jdbcType=VARCHAR},
        #{dictType,jdbcType=VARCHAR},
        #{dictTypeContent,jdbcType=VARCHAR},
        #{dictCode,jdbcType=VARCHAR},
        #{dictValue,jdbcType=VARCHAR},
        #{crtTime,jdbcType=VARCHAR},
        #{altTime,jdbcType=VARCHAR}
        )

    </insert>

    <select id="queryDictInfo" parameterType="java.util.Map" resultMap="BaseResultMap">
        select * from DICT_INFO
        <where>
            <if test="dictType!=null and dictType!=''">
                and DICT_TYPE=#{dictType,jdbcType=VARCHAR}
            </if>
        </where>
    </select>


    <select id="queryDictInfoByDictId" parameterType="String" resultMap="BaseResultMap">
        select * from DICT_INFO
        where DICT_ID = #{dictId,jdbcType=VARCHAR}
    </select>

    <select id="getDictTypeContent" parameterType="java.util.Map" resultMap="BaseResultMap">
        select DICT_TYPE_CONTENT from
         ( select DICT_TYPE_CONTENT,ROWNUM as rn from DICT_INFO where DICT_TYPE=#{dictType,jdbcType=VARCHAR} order by ALT_DATE desc ) a
         where a.rn=1

    </select>
    <update id="editDictInfo" parameterType="com.zuer.movieprojectdict.entity.Dict">

        update DICT_INFO
        set
        DICT_TYPE=#{dictType,jdbcType=VARCHAR},
        DICT_TYPE_CONTENT=#{dictTypeContent,jdbcType=VARCHAR},
        DICT_CODE=#{dictCode,jdbcType=VARCHAR},
        DICT_VALUE=#{dictValue,jdbcType=VARCHAR},
        ALT_DATE=sysdate
        where DICT_ID = #{dictId,jdbcType=VARCHAR}

    </update>

    <delete id="deleteDictInfoByDictId" parameterType="String">
        delete from DICT_INFO
        where DICT_ID = #{dictId,jdbcType=VARCHAR}
    </delete>

    <select id="queryDictInfoByDictTypeAndDictId" parameterType="String" resultMap="BaseResultMap">

        select * from
         ( select info.*,ROWNUM as rn from DICT_INFO info where
         DICT_TYPE=#{dictType,jdbcType=VARCHAR}
         AND DICT_CODE=#{dictCode,jdbcType=VARCHAR}
         order by ALT_DATE desc ) a
         where a.rn=1


    </select>
    <select id="queryDictInfoByDictType" parameterType="String" resultMap="BaseResultMap">
        select * from DICT_INFO where  DICT_TYPE=#{dictType,jdbcType=VARCHAR}
        order by DICT_CODE
    </select>

</mapper>